string_ops_subhra/__init__.py
string_ops_subhra/str_ops.py
stringoperations_subhra-1.0.1.dist-info/LICENSE.txt
stringoperations_subhra-1.0.1.dist-info/METADATA
stringoperations_subhra-1.0.1.dist-info/WHEEL
stringoperations_subhra-1.0.1.dist-info/top_level.txt
stringoperations_subhra-1.0.1.dist-info/RECORD
