Metadata-Version: 2.1
Name: stringoperations-subhra
Version: 1.0.1
Summary: Program to perform operations on string
Home-page: UNKNOWN
Author: Subhra Subudhi 
Author-email: subhra.subudhi@yahoo.com
License: MIT
Platform: UNKNOWN
Classifier: License :: OSI Approved :: MIT License
Classifier: Programming Language :: Python :: 3
Classifier: Programming Language :: Python :: 3.7
